{"recordsets":[[{"VNAME":"KRITI SAMARIA","GenAvgDeadTimePerBerthing":5.6},{"VNAME":"KRITI SEA","GenAvgDeadTimePerBerthing":5.6},{"VNAME":"OVERSEAS SUN COAST","GenAvgDeadTimePerBerthing":5.6},{"VNAME":"BARBAROS HAYRETTIN V","GenAvgDeadTimePerBerthing":5.9},{"VNAME":"MED ANTARCTIC","GenAvgDeadTimePerBerthing":6.141666},{"VNAME":"HIGH DISCOVERY","GenAvgDeadTimePerBerthing":6.166666},{"VNAME":"SFL LION","GenAvgDeadTimePerBerthing":6.3},{"VNAME":"ADA","GenAvgDeadTimePerBerthing":6.4},{"VNAME":"KOCATEPE","GenAvgDeadTimePerBerthing":6.5},{"VNAME":"OVERSEAS SANTORINI","GenAvgDeadTimePerBerthing":6.9},{"VNAME":"VS LEIA","GenAvgDeadTimePerBerthing":7.333333},{"VNAME":"STENA POLARIS","GenAvgDeadTimePerBerthing":7.375},{"VNAME":"STELLA MARIS","GenAvgDeadTimePerBerthing":7.825},{"VNAME":"PLUTO MOON","GenAvgDeadTimePerBerthing":8.35},{"VNAME":"SEAVEN VOYAGER","GenAvgDeadTimePerBerthing":8.4}]],"recordset":[{"VNAME":"KRITI SAMARIA","GenAvgDeadTimePerBerthing":5.6},{"VNAME":"KRITI SEA","GenAvgDeadTimePerBerthing":5.6},{"VNAME":"OVERSEAS SUN COAST","GenAvgDeadTimePerBerthing":5.6},{"VNAME":"BARBAROS HAYRETTIN V","GenAvgDeadTimePerBerthing":5.9},{"VNAME":"MED ANTARCTIC","GenAvgDeadTimePerBerthing":6.141666},{"VNAME":"HIGH DISCOVERY","GenAvgDeadTimePerBerthing":6.166666},{"VNAME":"SFL LION","GenAvgDeadTimePerBerthing":6.3},{"VNAME":"ADA","GenAvgDeadTimePerBerthing":6.4},{"VNAME":"KOCATEPE","GenAvgDeadTimePerBerthing":6.5},{"VNAME":"OVERSEAS SANTORINI","GenAvgDeadTimePerBerthing":6.9},{"VNAME":"VS LEIA","GenAvgDeadTimePerBerthing":7.333333},{"VNAME":"STENA POLARIS","GenAvgDeadTimePerBerthing":7.375},{"VNAME":"STELLA MARIS","GenAvgDeadTimePerBerthing":7.825},{"VNAME":"PLUTO MOON","GenAvgDeadTimePerBerthing":8.35},{"VNAME":"SEAVEN VOYAGER","GenAvgDeadTimePerBerthing":8.4}],"output":{},"rowsAffected":[],"returnValue":0}
